chronotask/__init__.py
chronotask/__main__.py
chronotask-0.1.1.dist-info/LICENSE
chronotask-0.1.1.dist-info/METADATA
chronotask-0.1.1.dist-info/WHEEL
chronotask-0.1.1.dist-info/RECORD
