Metadata-Version: 2.1
Name: chronotask
Version: 0.1.1
Summary: Simple python function call scheduler in crontab format
License: GPL-3.0-or-later
Author: Leo Feradero Nugraha
Author-email: leoferaderonugraha@gmail.com
Requires-Python: >=3.8,<4.0
Classifier: License :: OSI Approved :: GNU General Public License v3 or later (GPLv3+)
Classifier: Programming Language :: Python :: 3
Classifier: Programming Language :: Python :: 3.8
Classifier: Programming Language :: Python :: 3.9
Classifier: Programming Language :: Python :: 3.10
Classifier: Programming Language :: Python :: 3.11
Classifier: Programming Language :: Python :: 3.12
